scenex/__init__.py
scenex/py.typed
scenex/util.py
scenex/adaptors/__init__.py
scenex/adaptors/_auto.py
scenex/adaptors/_base.py
scenex/adaptors/_registry.py
scenex/adaptors/_pygfx/__init__.py
scenex/adaptors/_pygfx/_adaptor_registry.py
scenex/adaptors/_pygfx/_camera.py
scenex/adaptors/_pygfx/_canvas.py
scenex/adaptors/_pygfx/_image.py
scenex/adaptors/_pygfx/_node.py
scenex/adaptors/_pygfx/_points.py
scenex/adaptors/_pygfx/_scene.py
scenex/adaptors/_pygfx/_view.py
scenex/adaptors/_pygfx/_volume.py
scenex/adaptors/_vispy/__init__.py
scenex/adaptors/_vispy/_adaptor_registry.py
scenex/adaptors/_vispy/_camera.py
scenex/adaptors/_vispy/_canvas.py
scenex/adaptors/_vispy/_image.py
scenex/adaptors/_vispy/_node.py
scenex/adaptors/_vispy/_points.py
scenex/adaptors/_vispy/_scene.py
scenex/adaptors/_vispy/_view.py
scenex/adaptors/_vispy/_volume.py
scenex/model/__init__.py
scenex/model/_base.py
scenex/model/_canvas.py
scenex/model/_evented_list.py
scenex/model/_layout.py
scenex/model/_transform.py
scenex/model/_view.py
scenex/model/_nodes/__init__.py
scenex/model/_nodes/camera.py
scenex/model/_nodes/image.py
scenex/model/_nodes/node.py
scenex/model/_nodes/points.py
scenex/model/_nodes/scene.py
scenex/model/_nodes/volume.py
scenex-0.0.1.dist-info/METADATA
scenex-0.0.1.dist-info/WHEEL
scenex-0.0.1.dist-info/licenses/LICENSE
scenex-0.0.1.dist-info/RECORD
