Metadata-Version: 2.4
Name: scenex
Version: 0.0.1
Summary: Declarative scene graph model and backend abstraction.
Project-URL: homepage, https://github.com/pyapp-kit/scenex
Project-URL: repository, https://github.com/pyapp-kit/scenex
Author-email: Talley Lambert <talley.lambert@gmail.com>
License: BSD-3-Clause
License-File: LICENSE
Classifier: Development Status :: 3 - Alpha
Classifier: License :: OSI Approved :: BSD License
Classifier: Programming Language :: Python :: 3
Classifier: Programming Language :: Python :: 3.10
Classifier: Programming Language :: Python :: 3.11
Classifier: Programming Language :: Python :: 3.12
Classifier: Programming Language :: Python :: 3.13
Classifier: Typing :: Typed
Requires-Python: >=3.10
Requires-Dist: cmap>=0.5
Requires-Dist: numpy>=1.24
Requires-Dist: psygnal>=0.11.1
Requires-Dist: pydantic>=2.10
Provides-Extra: pygfx
Requires-Dist: pygfx>=0.9.0; extra == 'pygfx'
Provides-Extra: vispy
Requires-Dist: pyopengl; extra == 'vispy'
Requires-Dist: vispy>=0.15.0; extra == 'vispy'
